{
  "bmrs_boalf": {
    "table": "bmrs_boalf",
    "row_count": 9675190,
    "size_bytes": 1038069728,
    "creation_time": "2025-09-09 22:35:32.309000+00:00",
    "last_modified_time": "2025-09-21 11:05:02.745000+00:00",
    "max__ingested_utc": "2025-09-21 11:04:56.272007+00:00",
    "min__window_from_utc": "2022-01-01 00:00:00+00:00",
    "max__window_to_utc": "2025-09-21 00:00:00+00:00"
  },
  "bmrs_bod": {
    "table": "bmrs_bod",
    "row_count": 868109559,
    "size_bytes": 82713401311,
    "creation_time": "2025-09-09 22:36:13.647000+00:00",
    "last_modified_time": "2025-09-21 11:04:47.429000+00:00",
    "max__ingested_utc": "2025-09-21 11:04:41.564291+00:00",
    "min__window_from_utc": "2022-01-01 00:00:00+00:00",
    "max__window_to_utc": "2025-09-21 00:00:00+00:00"
  },
  "bmrs_freq": {
    "table": "bmrs_freq",
    "row_count": 19351192,
    "size_bytes": 390484561,
    "creation_time": "2025-09-09 22:36:51.163000+00:00",
    "last_modified_time": "2025-09-21 11:00:25.583000+00:00",
    "max__ingested_utc": "2025-09-21 11:00:19.317671+00:00",
    "min__window_from_utc": "2025-09-14 00:00:00+00:00",
    "max__window_to_utc": "2025-09-21 00:00:00+00:00"
  },
  "bmrs_fuelinst": {
    "table": "bmrs_fuelinst",
    "row_count": 64140,
    "size_bytes": 21894189,
    "creation_time": "2025-09-16 22:01:41.433000+00:00",
    "last_modified_time": "2025-09-21 11:00:34.353000+00:00",
    "max__ingested_utc": "2025-09-21 11:00:30.847884+00:00",
    "min__window_from_utc": "2025-09-14 00:00:00+00:00",
    "max__window_to_utc": "2025-09-21 00:00:00+00:00"
  },
  "bmrs_mels": {
    "table": "bmrs_mels",
    "row_count": 100885391,
    "size_bytes": 51277264960,
    "creation_time": "2025-09-09 22:38:28.623000+00:00",
    "last_modified_time": "2025-09-21 11:01:06.566000+00:00",
    "max__ingested_utc": "2025-09-21 11:00:42.806391+00:00",
    "min__window_from_utc": "2023-01-01 00:00:00+00:00",
    "max__window_to_utc": "2025-09-21 00:00:00+00:00"
  },
  "bmrs_mils": {
    "table": "bmrs_mils",
    "row_count": 98623246,
    "size_bytes": 49920441960,
    "creation_time": "2025-09-09 22:39:07.620000+00:00",
    "last_modified_time": "2025-09-21 11:01:50.774000+00:00",
    "max__ingested_utc": "2025-09-21 11:01:19.471189+00:00",
    "min__window_from_utc": "2023-01-01 00:00:00+00:00",
    "max__window_to_utc": "2025-09-21 00:00:00+00:00"
  },
  "bmrs_pn": {
    "table": "bmrs_pn",
    "row_count": 132563144,
    "size_bytes": 53100659165,
    "creation_time": "2025-09-12 11:44:27.664000+00:00",
    "last_modified_time": "2025-09-21 11:05:24.178000+00:00",
    "max__ingested_utc": "2025-09-21 11:05:09.561092+00:00",
    "min__window_from_utc": "2022-01-01 00:00:00+00:00",
    "max__window_to_utc": "2025-09-21 00:00:00+00:00"
  },
  "bmrs_qpn": {
    "table": "bmrs_qpn",
    "row_count": 117372028,
    "size_bytes": 47257503174,
    "creation_time": "2025-09-12 11:44:47.580000+00:00",
    "last_modified_time": "2025-09-21 11:05:54.664000+00:00",
    "max__ingested_utc": "2025-09-21 11:05:33.108850+00:00",
    "min__window_from_utc": "2022-01-01 00:00:00+00:00",
    "max__window_to_utc": "2025-09-21 00:00:00+00:00"
  }
}