{
  "bmrs_boalf": {
    "table": "bmrs_boalf",
    "row_count": 9771950,
    "size_bytes": 1050313704,
    "creation_time": "2025-09-09 22:35:32.309000+00:00",
    "last_modified_time": "2025-09-21 12:02:54.853000+00:00",
    "max__ingested_utc": "2025-09-21 12:02:45.085733+00:00",
    "min__window_from_utc": "2022-01-01 00:00:00+00:00",
    "max__window_to_utc": "2025-09-21 00:00:00+00:00"
  },
  "bmrs_bod": {
    "table": "bmrs_bod",
    "row_count": 869103655,
    "size_bytes": 82836974123,
    "creation_time": "2025-09-09 22:36:13.647000+00:00",
    "last_modified_time": "2025-09-21 12:02:38.513000+00:00",
    "max__ingested_utc": "2025-09-21 12:02:27.631725+00:00",
    "min__window_from_utc": "2022-01-01 00:00:00+00:00",
    "max__window_to_utc": "2025-09-21 00:00:00+00:00"
  },
  "bmrs_freq": {
    "table": "bmrs_freq",
    "row_count": 19374236,
    "size_bytes": 391680305,
    "creation_time": "2025-09-09 22:36:51.163000+00:00",
    "last_modified_time": "2025-09-21 12:00:26.560000+00:00",
    "max__ingested_utc": "2025-09-21 12:00:17.494921+00:00",
    "min__window_from_utc": "2025-09-14 00:00:00+00:00",
    "max__window_to_utc": "2025-09-21 00:00:00+00:00"
  },
  "bmrs_fuelinst": {
    "table": "bmrs_fuelinst",
    "row_count": 76200,
    "size_bytes": 26010870,
    "creation_time": "2025-09-16 22:01:41.433000+00:00",
    "last_modified_time": "2025-09-21 12:00:36.163000+00:00",
    "max__ingested_utc": "2025-09-21 12:00:32.871916+00:00",
    "min__window_from_utc": "2025-09-14 00:00:00+00:00",
    "max__window_to_utc": "2025-09-21 00:00:00+00:00"
  },
  "bmrs_mels": {
    "table": "bmrs_mels",
    "row_count": 101374415,
    "size_bytes": 51526012512,
    "creation_time": "2025-09-09 22:38:28.623000+00:00",
    "last_modified_time": "2025-09-21 12:01:05.990000+00:00",
    "max__ingested_utc": "2025-09-21 12:00:45.125114+00:00",
    "min__window_from_utc": "2023-01-01 00:00:00+00:00",
    "max__window_to_utc": "2025-09-21 00:00:00+00:00"
  },
  "bmrs_mils": {
    "table": "bmrs_mils",
    "row_count": 99075458,
    "size_bytes": 50150461232,
    "creation_time": "2025-09-09 22:39:07.620000+00:00",
    "last_modified_time": "2025-09-21 12:01:30.465000+00:00",
    "max__ingested_utc": "2025-09-21 12:01:14.054590+00:00",
    "min__window_from_utc": "2023-01-01 00:00:00+00:00",
    "max__window_to_utc": "2025-09-21 00:00:00+00:00"
  },
  "bmrs_pn": {
    "table": "bmrs_pn",
    "row_count": 133039140,
    "size_bytes": 53291377785,
    "creation_time": "2025-09-12 11:44:27.664000+00:00",
    "last_modified_time": "2025-09-21 12:04:22.875000+00:00",
    "max__ingested_utc": "2025-09-21 12:03:17.453356+00:00",
    "min__window_from_utc": "2022-01-01 00:00:00+00:00",
    "max__window_to_utc": "2025-09-21 00:00:00+00:00"
  },
  "bmrs_qpn": {
    "table": "bmrs_qpn",
    "row_count": 117798628,
    "size_bytes": 47429300974,
    "creation_time": "2025-09-12 11:44:47.580000+00:00",
    "last_modified_time": "2025-09-21 12:05:15.828000+00:00",
    "max__ingested_utc": "2025-09-21 12:04:58.433859+00:00",
    "min__window_from_utc": "2022-01-01 00:00:00+00:00",
    "max__window_to_utc": "2025-09-21 00:00:00+00:00"
  }
}